aprioripy/__init__.py
aprioripy-0.0.2.dist-info/LICENSE
aprioripy-0.0.2.dist-info/METADATA
aprioripy-0.0.2.dist-info/WHEEL
aprioripy-0.0.2.dist-info/top_level.txt
aprioripy-0.0.2.dist-info/RECORD
