Metadata-Version: 2.1
Name: aprioripy
Version: 0.0.2
Summary: Apriori algorithm.
Home-page: https://github.com/gokhangerdan/Aprioripy
Author: Gökhan Gerdan
Author-email: gokhang1327@gmail.com
License: UNKNOWN
Platform: UNKNOWN
Classifier: Programming Language :: Python :: 3
Classifier: License :: OSI Approved :: MIT License
Classifier: Operating System :: OS Independent
Requires-Python: >=3.6
